[
  {
    "id": "ce379372-2abc-4f72-b72f-da533632b3ee",
    "date": "2023-06-01",
    "amount": 501.28,
    "currency": "ILS",
    "type": "donation",
    "createdAt": "2023-06-01T00:00:00Z",
    "updatedAt": "2023-06-01T00:00:00Z",
    "description": "Zaka donation",
    "category": "Religious",
    "recipient": "Moshe Levi",
    "isRecurring": false
  },
  {
    "id": "cf7d4a5f-dd66-4fcd-9f19-7ebd906bc178",
    "date": "2023-06-01",
    "amount": 1534.48,
    "currency": "ILS",
    "type": "income",
    "createdAt": "2023-06-01T00:00:00Z",
    "updatedAt": "2023-06-01T00:00:00Z",
    "description": "Bonus",
    "category": "Freelance",
    "recipient": "Chabad House",
    "isRecurring": true,
    "isChomesh": false,
    "recurringDayOfMonth": 15,
    "recurringTotalCount": 6
  },
  {
    "id": "73d25a67-01ff-4358-9a37-ca40321ff2b9",
    "date": "2023-06-01",
    "amount": 1841.88,
    "currency": "ILS",
    "type": "income",
    "createdAt": "2023-06-01T00:00:00Z",
    "updatedAt": "2023-06-01T00:00:00Z",
    "description": "Salary",
    "category": "Freelance",
    "recipient": "Landlord",
    "isRecurring": false,
    "isChomesh": true
  },
  {
    "id": "5f236fec-6293-4df2-bd6d-6f1aa2fb75e9",
    "date": "2023-06-01",
    "amount": 1174.91,
    "currency": "ILS",
    "type": "income",
    "createdAt": "2023-06-01T00:00:00Z",
    "updatedAt": "2023-06-01T00:00:00Z",
    "description": "Freelance work",
    "category": "Salary",
    "recipient": "Employer",
    "isRecurring": false,
    "isChomesh": true
  },
  {
    "id": "e19f7d92-841a-4e8f-a03f-027ecc62487a",
    "date": "2023-06-01",
    "amount": 1601.27,
    "currency": "ILS",
    "type": "income",
    "createdAt": "2023-06-01T00:00:00Z",
    "updatedAt": "2023-06-01T00:00:00Z",
    "description": "Salary",
    "category": "Refund",
    "recipient": "Partner",
    "isRecurring": false,
    "isChomesh": true
  },
  {
    "id": "11ba0cf3-6ac7-46bf-9581-d008a2219406",
    "date": "2023-06-01",
    "amount": 1430.41,
    "currency": "ILS",
    "type": "donation",
    "createdAt": "2023-06-01T00:00:00Z",
    "updatedAt": "2023-06-01T00:00:00Z",
    "description": "Charity for children",
    "category": "Charity",
    "recipient": "Supplier",
    "isRecurring": false
  },
  {
    "id": "8ce4e727-1b86-4f1d-b611-632d8db2e947",
    "date": "2023-06-01",
    "amount": 1453.46,
    "currency": "ILS",
    "type": "donation",
    "createdAt": "2023-06-01T00:00:00Z",
    "updatedAt": "2023-06-01T00:00:00Z",
    "description": "Donation to synagogue",
    "category": "Charity",
    "recipient": "Employer",
    "isRecurring": true,
    "recurringDayOfMonth": 17,
    "recurringTotalCount": 8
  },
  {
    "id": "b725048a-34a4-4b66-9788-4b56ee0d407a",
    "date": "2023-06-01",
    "amount": 2474.19,
    "currency": "ILS",
    "type": "expense",
    "createdAt": "2023-06-01T00:00:00Z",
    "updatedAt": "2023-06-01T00:00:00Z",
    "description": "Restaurant",
    "category": "Living",
    "recipient": "Moshe Levi",
    "isRecurring": false
  },
  {
    "id": "24b1aa26-3f60-4056-b155-0edbb367e3aa",
    "date": "2023-07-01",
    "amount": 1097.98,
    "currency": "ILS",
    "type": "donation",
    "createdAt": "2023-07-01T00:00:00Z",
    "updatedAt": "2023-07-01T00:00:00Z",
    "description": "Donation to synagogue",
    "category": "Education",
    "recipient": "Electric Company",
    "isRecurring": false
  },
  {
    "id": "187fc7ed-aadb-4d9f-a099-1ec1c7d47f9e",
    "date": "2023-07-01",
    "amount": 2027.34,
    "currency": "ILS",
    "type": "recognized-expense",
    "createdAt": "2023-07-01T00:00:00Z",
    "updatedAt": "2023-07-01T00:00:00Z",
    "description": "Work travel",
    "category": "Tools",
    "recipient": "Yossi Cohen",
    "isRecurring": false
  },
  {
    "id": "754c51aa-ae61-4082-a59f-33f87ed0a1f9",
    "date": "2023-07-01",
    "amount": 553.74,
    "currency": "ILS",
    "type": "donation",
    "createdAt": "2023-07-01T00:00:00Z",
    "updatedAt": "2023-07-01T00:00:00Z",
    "description": "Donation to synagogue",
    "category": "Religious",
    "recipient": "Employer",
    "isRecurring": true,
    "recurringDayOfMonth": 8,
    "recurringTotalCount": 10
  },
  {
    "id": "b4f2aaba-2167-4fad-9248-3cec56b1fae3",
    "date": "2023-07-01",
    "amount": 2082.47,
    "currency": "ILS",
    "type": "expense",
    "createdAt": "2023-07-01T00:00:00Z",
    "updatedAt": "2023-07-01T00:00:00Z",
    "description": "Clothing",
    "category": "Transportation",
    "recipient": "Partner",
    "isRecurring": false
  },
  {
    "id": "aebc35f1-56d3-4ebe-9e2e-8c25e7042260",
    "date": "2023-07-01",
    "amount": 2002.2,
    "currency": "ILS",
    "type": "expense",
    "createdAt": "2023-07-01T00:00:00Z",
    "updatedAt": "2023-07-01T00:00:00Z",
    "description": "Rent",
    "category": "Entertainment",
    "recipient": "Supplier",
    "isRecurring": false
  },
  {
    "id": "f01fc06f-a977-4336-b558-13b76fde4a11",
    "date": "2023-07-01",
    "amount": 2034.01,
    "currency": "ILS",
    "type": "recognized-expense",
    "createdAt": "2023-07-01T00:00:00Z",
    "updatedAt": "2023-07-01T00:00:00Z",
    "description": "Work travel",
    "category": "Business",
    "recipient": "Partner",
    "isRecurring": false
  },
  {
    "id": "77320c4f-dc81-436f-a2b1-4cfefa81c9de",
    "date": "2023-07-01",
    "amount": 1465.99,
    "currency": "ILS",
    "type": "expense",
    "createdAt": "2023-07-01T00:00:00Z",
    "updatedAt": "2023-07-01T00:00:00Z",
    "description": "Rent",
    "category": "Utilities",
    "recipient": "Partner",
    "isRecurring": false
  },
  {
    "id": "2db1a41d-39db-46c7-bf67-792a4970b867",
    "date": "2023-07-01",
    "amount": 1913.45,
    "currency": "ILS",
    "type": "expense",
    "createdAt": "2023-07-01T00:00:00Z",
    "updatedAt": "2023-07-01T00:00:00Z",
    "description": "Clothing",
    "category": "Transportation",
    "recipient": "Employer",
    "isRecurring": false
  },
  {
    "id": "04bf3f9f-006b-453c-8f45-4fdc996caede",
    "date": "2023-08-01",
    "amount": 1764.31,
    "currency": "ILS",
    "type": "donation",
    "createdAt": "2023-08-01T00:00:00Z",
    "updatedAt": "2023-08-01T00:00:00Z",
    "description": "Donation to synagogue",
    "category": "Education",
    "recipient": "Chabad House",
    "isRecurring": false
  },
  {
    "id": "702e3457-7bd2-4233-9d47-ff734799620f",
    "date": "2023-08-01",
    "amount": 2432.42,
    "currency": "ILS",
    "type": "recognized-expense",
    "createdAt": "2023-08-01T00:00:00Z",
    "updatedAt": "2023-08-01T00:00:00Z",
    "description": "Business meal",
    "category": "Business",
    "recipient": "Landlord",
    "isRecurring": true,
    "recurringDayOfMonth": 4,
    "recurringTotalCount": 7
  },
  {
    "id": "4f54a9ba-8aba-40f0-be67-0f5baa30f40d",
    "date": "2023-08-01",
    "amount": 1991.87,
    "currency": "ILS",
    "type": "donation",
    "createdAt": "2023-08-01T00:00:00Z",
    "updatedAt": "2023-08-01T00:00:00Z",
    "description": "Charity for children",
    "category": "Charity",
    "recipient": "Partner",
    "isRecurring": false
  },
  {
    "id": "0bb4f823-24f9-4a53-a2aa-ba82a53310f3",
    "date": "2023-08-01",
    "amount": 1711.9,
    "currency": "ILS",
    "type": "expense",
    "createdAt": "2023-08-01T00:00:00Z",
    "updatedAt": "2023-08-01T00:00:00Z",
    "description": "Fuel",
    "category": "Living",
    "recipient": "Supplier",
    "isRecurring": false
  },
  {
    "id": "28a7782f-660e-404b-8e3e-23d62684b52a",
    "date": "2023-08-01",
    "amount": 2114.75,
    "currency": "ILS",
    "type": "recognized-expense",
    "createdAt": "2023-08-01T00:00:00Z",
    "updatedAt": "2023-08-01T00:00:00Z",
    "description": "Conference ticket",
    "category": "Business",
    "recipient": "Chabad House",
    "isRecurring": false
  },
  {
    "id": "f76cb28a-0437-4001-9dbd-f17154aec085",
    "date": "2023-08-01",
    "amount": 1075.74,
    "currency": "ILS",
    "type": "donation",
    "createdAt": "2023-08-01T00:00:00Z",
    "updatedAt": "2023-08-01T00:00:00Z",
    "description": "Zaka donation",
    "category": "Education",
    "recipient": "Electric Company",
    "isRecurring": false
  },
  {
    "id": "e49e8e0a-74f5-4c41-95ca-4a5eac36d111",
    "date": "2023-08-01",
    "amount": 2120.19,
    "currency": "ILS",
    "type": "recognized-expense",
    "createdAt": "2023-08-01T00:00:00Z",
    "updatedAt": "2023-08-01T00:00:00Z",
    "description": "Work travel",
    "category": "Tools",
    "recipient": "Employer",
    "isRecurring": false
  },
  {
    "id": "e6b4d49a-cdad-4a78-ba61-4eac3be4f7ad",
    "date": "2023-08-01",
    "amount": 1680.95,
    "currency": "ILS",
    "type": "expense",
    "createdAt": "2023-08-01T00:00:00Z",
    "updatedAt": "2023-08-01T00:00:00Z",
    "description": "Internet",
    "category": "Living",
    "recipient": "Employer",
    "isRecurring": true,
    "recurringDayOfMonth": 21,
    "recurringTotalCount": 11
  },
  {
    "id": "3bb200fc-ec0c-4691-b9fe-64aabbb7cf17",
    "date": "2023-09-01",
    "amount": 1859.93,
    "currency": "ILS",
    "type": "income",
    "createdAt": "2023-09-01T00:00:00Z",
    "updatedAt": "2023-09-01T00:00:00Z",
    "description": "Salary",
    "category": "Salary",
    "recipient": "Chabad House",
    "isRecurring": false,
    "isChomesh": true
  },
  {
    "id": "9b0b8f70-14bb-4a8a-95a0-c2f7a3ff5af6",
    "date": "2023-09-01",
    "amount": 904.61,
    "currency": "ILS",
    "type": "income",
    "createdAt": "2023-09-01T00:00:00Z",
    "updatedAt": "2023-09-01T00:00:00Z",
    "description": "Bonus",
    "category": "Refund",
    "recipient": "Yossi Cohen",
    "isRecurring": false,
    "isChomesh": true
  },
  {
    "id": "7c48d738-0e6b-4965-8681-622375e86405",
    "date": "2023-09-01",
    "amount": 878.78,
    "currency": "ILS",
    "type": "recognized-expense",
    "createdAt": "2023-09-01T00:00:00Z",
    "updatedAt": "2023-09-01T00:00:00Z",
    "description": "Conference ticket",
    "category": "Business",
    "recipient": "Landlord",
    "isRecurring": false
  },
  {
    "id": "cc990140-9923-41e7-8a02-da67e8d53c1c",
    "date": "2023-09-01",
    "amount": 1867.49,
    "currency": "ILS",
    "type": "expense",
    "createdAt": "2023-09-01T00:00:00Z",
    "updatedAt": "2023-09-01T00:00:00Z",
    "description": "Internet",
    "category": "Entertainment",
    "recipient": "Landlord",
    "isRecurring": true,
    "recurringDayOfMonth": 21,
    "recurringTotalCount": 4
  },
  {
    "id": "8ac2b70a-c385-4652-9d4e-d0e7bbd99912",
    "date": "2023-09-01",
    "amount": 2139.65,
    "currency": "ILS",
    "type": "expense",
    "createdAt": "2023-09-01T00:00:00Z",
    "updatedAt": "2023-09-01T00:00:00Z",
    "description": "Restaurant",
    "category": "Transportation",
    "recipient": "Electric Company",
    "isRecurring": false
  },
  {
    "id": "2643bd65-7b47-474f-a85f-3c339340f7fb",
    "date": "2023-09-01",
    "amount": 961.75,
    "currency": "ILS",
    "type": "recognized-expense",
    "createdAt": "2023-09-01T00:00:00Z",
    "updatedAt": "2023-09-01T00:00:00Z",
    "description": "Software subscription",
    "category": "Tools",
    "recipient": "Employer",
    "isRecurring": false
  },
  {
    "id": "e887bd56-0c3f-4c07-b6d6-7b3e9112488b",
    "date": "2023-09-01",
    "amount": 2405.05,
    "currency": "ILS",
    "type": "donation",
    "createdAt": "2023-09-01T00:00:00Z",
    "updatedAt": "2023-09-01T00:00:00Z",
    "description": "Donation to synagogue",
    "category": "Education",
    "recipient": "Electric Company",
    "isRecurring": true,
    "recurringDayOfMonth": 5,
    "recurringTotalCount": 10
  },
  {
    "id": "ee54895d-6880-44a7-b7ad-80ffa97e77b8",
    "date": "2023-09-01",
    "amount": 1273.85,
    "currency": "ILS",
    "type": "recognized-expense",
    "createdAt": "2023-09-01T00:00:00Z",
    "updatedAt": "2023-09-01T00:00:00Z",
    "description": "Business meal",
    "category": "Tools",
    "recipient": "Supplier",
    "isRecurring": false
  },
  {
    "id": "5e9342dc-cbe9-4e90-b129-c946fc914923",
    "date": "2023-10-01",
    "amount": 2259.24,
    "currency": "ILS",
    "type": "expense",
    "createdAt": "2023-10-01T00:00:00Z",
    "updatedAt": "2023-10-01T00:00:00Z",
    "description": "Fuel",
    "category": "Utilities",
    "recipient": "Chabad House",
    "isRecurring": false
  },
  {
    "id": "6cd19e80-d1fd-4ff0-aee8-da8d6bdd4ef9",
    "date": "2023-10-01",
    "amount": 1287.77,
    "currency": "ILS",
    "type": "recognized-expense",
    "createdAt": "2023-10-01T00:00:00Z",
    "updatedAt": "2023-10-01T00:00:00Z",
    "description": "Business meal",
    "category": "Training",
    "recipient": "Electric Company",
    "isRecurring": false
  },
  {
    "id": "bf209201-d277-469e-a1f3-2f55766f982b",
    "date": "2023-10-01",
    "amount": 1426.05,
    "currency": "ILS",
    "type": "income",
    "createdAt": "2023-10-01T00:00:00Z",
    "updatedAt": "2023-10-01T00:00:00Z",
    "description": "Freelance work",
    "category": "Salary",
    "recipient": "Chabad House",
    "isRecurring": false,
    "isChomesh": false
  },
  {
    "id": "084a3b47-119b-41fe-b65f-0ca3c86a57c1",
    "date": "2023-10-01",
    "amount": 1481.37,
    "currency": "ILS",
    "type": "donation",
    "createdAt": "2023-10-01T00:00:00Z",
    "updatedAt": "2023-10-01T00:00:00Z",
    "description": "Yeshiva support",
    "category": "Education",
    "recipient": "Partner",
    "isRecurring": true,
    "recurringDayOfMonth": 9,
    "recurringTotalCount": 4
  },
  {
    "id": "9f95e618-3183-4e2c-a9b5-ab11d5dcbdb9",
    "date": "2023-10-01",
    "amount": 986.01,
    "currency": "ILS",
    "type": "recognized-expense",
    "createdAt": "2023-10-01T00:00:00Z",
    "updatedAt": "2023-10-01T00:00:00Z",
    "description": "Software subscription",
    "category": "Tools",
    "recipient": "Chabad House",
    "isRecurring": false
  },
  {
    "id": "9770e221-bc55-4def-bd1b-e966f1cf7ee8",
    "date": "2023-10-01",
    "amount": 1613.1,
    "currency": "ILS",
    "type": "expense",
    "createdAt": "2023-10-01T00:00:00Z",
    "updatedAt": "2023-10-01T00:00:00Z",
    "description": "Fuel",
    "category": "Living",
    "recipient": "Supplier",
    "isRecurring": false
  },
  {
    "id": "304bd8d7-ded2-481c-ada3-3eed88d52929",
    "date": "2023-10-01",
    "amount": 2238.8,
    "currency": "ILS",
    "type": "recognized-expense",
    "createdAt": "2023-10-01T00:00:00Z",
    "updatedAt": "2023-10-01T00:00:00Z",
    "description": "Conference ticket",
    "category": "Training",
    "recipient": "Supplier",
    "isRecurring": false
  },
  {
    "id": "4fcd0e64-4310-492d-9600-83bd46d21ebf",
    "date": "2023-10-01",
    "amount": 2326.41,
    "currency": "ILS",
    "type": "recognized-expense",
    "createdAt": "2023-10-01T00:00:00Z",
    "updatedAt": "2023-10-01T00:00:00Z",
    "description": "Business meal",
    "category": "Business",
    "recipient": "Partner",
    "isRecurring": true,
    "recurringDayOfMonth": 18,
    "recurringTotalCount": 7
  },
  {
    "id": "ae53b86b-e422-4ea1-b9fc-9136392d578e",
    "date": "2023-11-01",
    "amount": 1174.35,
    "currency": "ILS",
    "type": "recognized-expense",
    "createdAt": "2023-11-01T00:00:00Z",
    "updatedAt": "2023-11-01T00:00:00Z",
    "description": "Conference ticket",
    "category": "Training",
    "recipient": "Yossi Cohen",
    "isRecurring": false
  },
  {
    "id": "41837e86-ebe9-4492-944b-87b3a878f9ba",
    "date": "2023-11-01",
    "amount": 793.67,
    "currency": "ILS",
    "type": "income",
    "createdAt": "2023-11-01T00:00:00Z",
    "updatedAt": "2023-11-01T00:00:00Z",
    "description": "Refund",
    "category": "Salary",
    "recipient": "Partner",
    "isRecurring": false,
    "isChomesh": true
  },
  {
    "id": "378bc981-ccd8-4d5a-b45f-ec8b06a2b9ff",
    "date": "2023-11-01",
    "amount": 1322.79,
    "currency": "ILS",
    "type": "recognized-expense",
    "createdAt": "2023-11-01T00:00:00Z",
    "updatedAt": "2023-11-01T00:00:00Z",
    "description": "Work travel",
    "category": "Business",
    "recipient": "Moshe Levi",
    "isRecurring": false
  },
  {
    "id": "44af667b-3781-48ea-95dc-7197e5f2f8d0",
    "date": "2023-11-01",
    "amount": 131.13,
    "currency": "ILS",
    "type": "expense",
    "createdAt": "2023-11-01T00:00:00Z",
    "updatedAt": "2023-11-01T00:00:00Z",
    "description": "Electricity bill",
    "category": "Living",
    "recipient": "Landlord",
    "isRecurring": false
  },
  {
    "id": "2666c73e-c28b-4de2-af25-98562b973471",
    "date": "2023-11-01",
    "amount": 224.24,
    "currency": "ILS",
    "type": "expense",
    "createdAt": "2023-11-01T00:00:00Z",
    "updatedAt": "2023-11-01T00:00:00Z",
    "description": "Fuel",
    "category": "Living",
    "recipient": "Supplier",
    "isRecurring": false
  },
  {
    "id": "9d54160b-f86e-4afd-bf29-02468c052121",
    "date": "2023-11-01",
    "amount": 417.15,
    "currency": "ILS",
    "type": "recognized-expense",
    "createdAt": "2023-11-01T00:00:00Z",
    "updatedAt": "2023-11-01T00:00:00Z",
    "description": "Business meal",
    "category": "Business",
    "recipient": "Electric Company",
    "isRecurring": false
  },
  {
    "id": "4a6b9627-da69-445d-b28d-7cc5d9fa44e6",
    "date": "2023-11-01",
    "amount": 1876.32,
    "currency": "ILS",
    "type": "donation",
    "createdAt": "2023-11-01T00:00:00Z",
    "updatedAt": "2023-11-01T00:00:00Z",
    "description": "Yeshiva support",
    "category": "Education",
    "recipient": "Supplier",
    "isRecurring": false
  },
  {
    "id": "437ed615-002e-4d7e-802c-bf6cb37266e0",
    "date": "2023-11-01",
    "amount": 514.03,
    "currency": "ILS",
    "type": "recognized-expense",
    "createdAt": "2023-11-01T00:00:00Z",
    "updatedAt": "2023-11-01T00:00:00Z",
    "description": "Business meal",
    "category": "Business",
    "recipient": "Moshe Levi",
    "isRecurring": false
  },
  {
    "id": "73288daf-1054-4a7f-bd4d-cf497e03d4c5",
    "date": "2023-12-01",
    "amount": 853.77,
    "currency": "ILS",
    "type": "expense",
    "createdAt": "2023-12-01T00:00:00Z",
    "updatedAt": "2023-12-01T00:00:00Z",
    "description": "Groceries",
    "category": "Utilities",
    "recipient": "Landlord",
    "isRecurring": false
  },
  {
    "id": "e0fdc639-5aa3-4210-9bda-4c31fc19e2b0",
    "date": "2023-12-01",
    "amount": 2334.08,
    "currency": "ILS",
    "type": "recognized-expense",
    "createdAt": "2023-12-01T00:00:00Z",
    "updatedAt": "2023-12-01T00:00:00Z",
    "description": "Work travel",
    "category": "Training",
    "recipient": "Partner",
    "isRecurring": false
  },
  {
    "id": "b6555fa9-9d8c-4faf-8703-d186bccc6270",
    "date": "2023-12-01",
    "amount": 417.26,
    "currency": "ILS",
    "type": "recognized-expense",
    "createdAt": "2023-12-01T00:00:00Z",
    "updatedAt": "2023-12-01T00:00:00Z",
    "description": "Conference ticket",
    "category": "Training",
    "recipient": "Partner",
    "isRecurring": false
  },
  {
    "id": "a61ccafb-71a1-4342-bfef-300fe8d6d2ac",
    "date": "2023-12-01",
    "amount": 793.56,
    "currency": "ILS",
    "type": "expense",
    "createdAt": "2023-12-01T00:00:00Z",
    "updatedAt": "2023-12-01T00:00:00Z",
    "description": "Clothing",
    "category": "Food",
    "recipient": "Electric Company",
    "isRecurring": false
  },
  {
    "id": "77ae4d59-8c6e-4782-b910-3dbbcf85620a",
    "date": "2023-12-01",
    "amount": 1878.43,
    "currency": "ILS",
    "type": "donation",
    "createdAt": "2023-12-01T00:00:00Z",
    "updatedAt": "2023-12-01T00:00:00Z",
    "description": "Zaka donation",
    "category": "Education",
    "recipient": "Electric Company",
    "isRecurring": false
  },
  {
    "id": "ce5dd62e-b8c0-4eef-b63b-5fd32ce24391",
    "date": "2023-12-01",
    "amount": 2153.18,
    "currency": "ILS",
    "type": "donation",
    "createdAt": "2023-12-01T00:00:00Z",
    "updatedAt": "2023-12-01T00:00:00Z",
    "description": "Yeshiva support",
    "category": "Religious",
    "recipient": "Chabad House",
    "isRecurring": false
  },
  {
    "id": "ce994cab-76f3-44a0-9802-2c05bf271938",
    "date": "2023-12-01",
    "amount": 2438.12,
    "currency": "ILS",
    "type": "recognized-expense",
    "createdAt": "2023-12-01T00:00:00Z",
    "updatedAt": "2023-12-01T00:00:00Z",
    "description": "Conference ticket",
    "category": "Business",
    "recipient": "Employer",
    "isRecurring": false
  },
  {
    "id": "52cdf2ba-f109-479b-8a94-8809795df9f9",
    "date": "2023-12-01",
    "amount": 1592.48,
    "currency": "ILS",
    "type": "donation",
    "createdAt": "2023-12-01T00:00:00Z",
    "updatedAt": "2023-12-01T00:00:00Z",
    "description": "Yeshiva support",
    "category": "Religious",
    "recipient": "Yossi Cohen",
    "isRecurring": false
  },
  {
    "id": "88ad6b6a-06c9-407a-9d01-326657f49c3d",
    "date": "2024-01-01",
    "amount": 1140.06,
    "currency": "ILS",
    "type": "expense",
    "createdAt": "2024-01-01T00:00:00Z",
    "updatedAt": "2024-01-01T00:00:00Z",
    "description": "Restaurant",
    "category": "Living",
    "recipient": "Electric Company",
    "isRecurring": true,
    "recurringDayOfMonth": 2,
    "recurringTotalCount": 7
  },
  {
    "id": "617968b8-a6df-4b14-a2fe-65afed43f072",
    "date": "2024-01-01",
    "amount": 833.97,
    "currency": "ILS",
    "type": "expense",
    "createdAt": "2024-01-01T00:00:00Z",
    "updatedAt": "2024-01-01T00:00:00Z",
    "description": "Fuel",
    "category": "Utilities",
    "recipient": "Yossi Cohen",
    "isRecurring": false
  },
  {
    "id": "d16adf74-328d-4a78-b4c3-26be21eae125",
    "date": "2024-01-01",
    "amount": 858.03,
    "currency": "ILS",
    "type": "income",
    "createdAt": "2024-01-01T00:00:00Z",
    "updatedAt": "2024-01-01T00:00:00Z",
    "description": "Refund",
    "category": "Freelance",
    "recipient": "Partner",
    "isRecurring": false,
    "isChomesh": true
  },
  {
    "id": "d7b79347-2c75-4e6f-b91f-7e4b652a57ca",
    "date": "2024-01-01",
    "amount": 2114.48,
    "currency": "ILS",
    "type": "expense",
    "createdAt": "2024-01-01T00:00:00Z",
    "updatedAt": "2024-01-01T00:00:00Z",
    "description": "Groceries",
    "category": "Utilities",
    "recipient": "Partner",
    "isRecurring": false
  },
  {
    "id": "9c6ad898-9a13-4ad5-aad3-47b25fb1a22c",
    "date": "2024-01-01",
    "amount": 499.13,
    "currency": "ILS",
    "type": "donation",
    "createdAt": "2024-01-01T00:00:00Z",
    "updatedAt": "2024-01-01T00:00:00Z",
    "description": "Charity for children",
    "category": "Education",
    "recipient": "Partner",
    "isRecurring": false
  },
  {
    "id": "681e670e-0ffa-42cd-9134-4d31cf8501c6",
    "date": "2024-01-01",
    "amount": 1310.27,
    "currency": "ILS",
    "type": "income",
    "createdAt": "2024-01-01T00:00:00Z",
    "updatedAt": "2024-01-01T00:00:00Z",
    "description": "Freelance work",
    "category": "Refund",
    "recipient": "Electric Company",
    "isRecurring": false,
    "isChomesh": true
  },
  {
    "id": "cda4ba43-f7ed-4a82-a422-e613b89f5a77",
    "date": "2024-01-01",
    "amount": 262.35,
    "currency": "ILS",
    "type": "expense",
    "createdAt": "2024-01-01T00:00:00Z",
    "updatedAt": "2024-01-01T00:00:00Z",
    "description": "Fuel",
    "category": "Entertainment",
    "recipient": "Electric Company",
    "isRecurring": false
  },
  {
    "id": "0c9a7180-9f4c-4517-85b8-7c64f889572c",
    "date": "2024-01-01",
    "amount": 877.99,
    "currency": "ILS",
    "type": "expense",
    "createdAt": "2024-01-01T00:00:00Z",
    "updatedAt": "2024-01-01T00:00:00Z",
    "description": "Restaurant",
    "category": "Food",
    "recipient": "Employer",
    "isRecurring": false
  },
  {
    "id": "c861e90b-19a7-46c9-846d-6870603880f7",
    "date": "2024-02-01",
    "amount": 198.37,
    "currency": "ILS",
    "type": "donation",
    "createdAt": "2024-02-01T00:00:00Z",
    "updatedAt": "2024-02-01T00:00:00Z",
    "description": "Charity for children",
    "category": "Charity",
    "recipient": "Moshe Levi",
    "isRecurring": false
  },
  {
    "id": "e0926c8f-d057-4f6b-bb9b-61b124f7c06e",
    "date": "2024-02-01",
    "amount": 154.03,
    "currency": "ILS",
    "type": "expense",
    "createdAt": "2024-02-01T00:00:00Z",
    "updatedAt": "2024-02-01T00:00:00Z",
    "description": "Rent",
    "category": "Utilities",
    "recipient": "Employer",
    "isRecurring": false
  },
  {
    "id": "07f5f6d3-a57b-4ceb-ae04-3794edea6278",
    "date": "2024-02-01",
    "amount": 1491.14,
    "currency": "ILS",
    "type": "income",
    "createdAt": "2024-02-01T00:00:00Z",
    "updatedAt": "2024-02-01T00:00:00Z",
    "description": "Salary",
    "category": "Freelance",
    "recipient": "Chabad House",
    "isRecurring": false,
    "isChomesh": false
  },
  {
    "id": "7c4d7388-c2d8-4313-b389-004c65fe2bcd",
    "date": "2024-02-01",
    "amount": 313.7,
    "currency": "ILS",
    "type": "expense",
    "createdAt": "2024-02-01T00:00:00Z",
    "updatedAt": "2024-02-01T00:00:00Z",
    "description": "Electricity bill",
    "category": "Utilities",
    "recipient": "Moshe Levi",
    "isRecurring": true,
    "recurringDayOfMonth": 5,
    "recurringTotalCount": 2
  },
  {
    "id": "dbd59393-836a-4025-b649-4018c272b6bf",
    "date": "2024-02-01",
    "amount": 885.23,
    "currency": "ILS",
    "type": "donation",
    "createdAt": "2024-02-01T00:00:00Z",
    "updatedAt": "2024-02-01T00:00:00Z",
    "description": "Zaka donation",
    "category": "Education",
    "recipient": "Yossi Cohen",
    "isRecurring": false
  },
  {
    "id": "11f5da2d-de7c-416c-a8e7-5db6dd2d94f4",
    "date": "2024-02-01",
    "amount": 1258.53,
    "currency": "ILS",
    "type": "donation",
    "createdAt": "2024-02-01T00:00:00Z",
    "updatedAt": "2024-02-01T00:00:00Z",
    "description": "Charity for children",
    "category": "Charity",
    "recipient": "Moshe Levi",
    "isRecurring": false
  },
  {
    "id": "edb3c7f8-f45f-4912-bd23-9af851ad95f1",
    "date": "2024-02-01",
    "amount": 2117.45,
    "currency": "ILS",
    "type": "recognized-expense",
    "createdAt": "2024-02-01T00:00:00Z",
    "updatedAt": "2024-02-01T00:00:00Z",
    "description": "Software subscription",
    "category": "Tools",
    "recipient": "Electric Company",
    "isRecurring": false
  },
  {
    "id": "87d27bbf-cf70-40a8-9e85-f3066fe88479",
    "date": "2024-02-01",
    "amount": 1149.91,
    "currency": "ILS",
    "type": "expense",
    "createdAt": "2024-02-01T00:00:00Z",
    "updatedAt": "2024-02-01T00:00:00Z",
    "description": "Fuel",
    "category": "Living",
    "recipient": "Moshe Levi",
    "isRecurring": false
  },
  {
    "id": "99755cb9-e802-42ca-8110-ec0d9d8be190",
    "date": "2024-03-01",
    "amount": 1605.34,
    "currency": "ILS",
    "type": "expense",
    "createdAt": "2024-03-01T00:00:00Z",
    "updatedAt": "2024-03-01T00:00:00Z",
    "description": "Clothing",
    "category": "Living",
    "recipient": "Yossi Cohen",
    "isRecurring": false
  },
  {
    "id": "cac204a3-c242-474b-a851-48cbb848368c",
    "date": "2024-03-01",
    "amount": 468.75,
    "currency": "ILS",
    "type": "donation",
    "createdAt": "2024-03-01T00:00:00Z",
    "updatedAt": "2024-03-01T00:00:00Z",
    "description": "Donation to synagogue",
    "category": "Education",
    "recipient": "Employer",
    "isRecurring": false
  },
  {
    "id": "c37ec7ef-6fb2-47af-a59c-8471a2dd1d04",
    "date": "2024-03-01",
    "amount": 625.39,
    "currency": "ILS",
    "type": "income",
    "createdAt": "2024-03-01T00:00:00Z",
    "updatedAt": "2024-03-01T00:00:00Z",
    "description": "Refund",
    "category": "Freelance",
    "recipient": "Supplier",
    "isRecurring": true,
    "isChomesh": false,
    "recurringDayOfMonth": 11,
    "recurringTotalCount": 7
  },
  {
    "id": "2e7ccecc-507d-4835-a11e-9dd7d808c7d0",
    "date": "2024-03-01",
    "amount": 538.88,
    "currency": "ILS",
    "type": "donation",
    "createdAt": "2024-03-01T00:00:00Z",
    "updatedAt": "2024-03-01T00:00:00Z",
    "description": "Yeshiva support",
    "category": "Charity",
    "recipient": "Chabad House",
    "isRecurring": false
  },
  {
    "id": "270febc3-e644-43b8-a237-a097be4378b4",
    "date": "2024-03-01",
    "amount": 50.07,
    "currency": "ILS",
    "type": "recognized-expense",
    "createdAt": "2024-03-01T00:00:00Z",
    "updatedAt": "2024-03-01T00:00:00Z",
    "description": "Business meal",
    "category": "Tools",
    "recipient": "Electric Company",
    "isRecurring": false
  },
  {
    "id": "22a199f0-fc07-4dae-aa9c-2742137dcc8e",
    "date": "2024-03-01",
    "amount": 1109.02,
    "currency": "ILS",
    "type": "expense",
    "createdAt": "2024-03-01T00:00:00Z",
    "updatedAt": "2024-03-01T00:00:00Z",
    "description": "Restaurant",
    "category": "Food",
    "recipient": "Landlord",
    "isRecurring": false
  },
  {
    "id": "1481e843-e7f6-44f6-b434-8b6ca2806975",
    "date": "2024-03-01",
    "amount": 672.77,
    "currency": "ILS",
    "type": "donation",
    "createdAt": "2024-03-01T00:00:00Z",
    "updatedAt": "2024-03-01T00:00:00Z",
    "description": "Yeshiva support",
    "category": "Religious",
    "recipient": "Yossi Cohen",
    "isRecurring": false
  },
  {
    "id": "8b853d07-4c39-4586-a0c0-eb8ee7b8307b",
    "date": "2024-03-01",
    "amount": 2360.71,
    "currency": "ILS",
    "type": "expense",
    "createdAt": "2024-03-01T00:00:00Z",
    "updatedAt": "2024-03-01T00:00:00Z",
    "description": "Clothing",
    "category": "Entertainment",
    "recipient": "Moshe Levi",
    "isRecurring": true,
    "recurringDayOfMonth": 6,
    "recurringTotalCount": 3
  },
  {
    "id": "1688c47c-827d-415f-b131-012f3b632fd0",
    "date": "2024-04-01",
    "amount": 827.48,
    "currency": "ILS",
    "type": "recognized-expense",
    "createdAt": "2024-04-01T00:00:00Z",
    "updatedAt": "2024-04-01T00:00:00Z",
    "description": "Conference ticket",
    "category": "Business",
    "recipient": "Landlord",
    "isRecurring": false
  },
  {
    "id": "63210323-1d91-4983-9ad2-5e19908cb588",
    "date": "2024-04-01",
    "amount": 1128.32,
    "currency": "ILS",
    "type": "expense",
    "createdAt": "2024-04-01T00:00:00Z",
    "updatedAt": "2024-04-01T00:00:00Z",
    "description": "Phone bill",
    "category": "Utilities",
    "recipient": "Landlord",
    "isRecurring": false
  },
  {
    "id": "ef5e517c-ace1-481b-9cbe-8f40e0ea2726",
    "date": "2024-04-01",
    "amount": 1916.05,
    "currency": "ILS",
    "type": "income",
    "createdAt": "2024-04-01T00:00:00Z",
    "updatedAt": "2024-04-01T00:00:00Z",
    "description": "Bonus",
    "category": "Salary",
    "recipient": "Chabad House",
    "isRecurring": false,
    "isChomesh": false
  },
  {
    "id": "d9ee906e-5b63-4f6b-86c9-827ef9e14724",
    "date": "2024-04-01",
    "amount": 1649.47,
    "currency": "ILS",
    "type": "expense",
    "createdAt": "2024-04-01T00:00:00Z",
    "updatedAt": "2024-04-01T00:00:00Z",
    "description": "Groceries",
    "category": "Utilities",
    "recipient": "Supplier",
    "isRecurring": false
  },
  {
    "id": "ad86f3f3-611f-4233-bafc-3ddcaeae19fe",
    "date": "2024-04-01",
    "amount": 2042.85,
    "currency": "ILS",
    "type": "expense",
    "createdAt": "2024-04-01T00:00:00Z",
    "updatedAt": "2024-04-01T00:00:00Z",
    "description": "Internet",
    "category": "Transportation",
    "recipient": "Yossi Cohen",
    "isRecurring": false
  },
  {
    "id": "10aa7b2c-a125-40af-97af-a196a00d158a",
    "date": "2024-04-01",
    "amount": 725.57,
    "currency": "ILS",
    "type": "expense",
    "createdAt": "2024-04-01T00:00:00Z",
    "updatedAt": "2024-04-01T00:00:00Z",
    "description": "Groceries",
    "category": "Entertainment",
    "recipient": "Yossi Cohen",
    "isRecurring": false
  },
  {
    "id": "0948c84e-e913-4879-9607-27a405e1c5cb",
    "date": "2024-04-01",
    "amount": 793.85,
    "currency": "ILS",
    "type": "income",
    "createdAt": "2024-04-01T00:00:00Z",
    "updatedAt": "2024-04-01T00:00:00Z",
    "description": "Refund",
    "category": "Refund",
    "recipient": "Employer",
    "isRecurring": false,
    "isChomesh": true
  },
  {
    "id": "3d1522dc-5ca8-409f-a037-4dbf4e18070c",
    "date": "2024-04-01",
    "amount": 1160.28,
    "currency": "ILS",
    "type": "recognized-expense",
    "createdAt": "2024-04-01T00:00:00Z",
    "updatedAt": "2024-04-01T00:00:00Z",
    "description": "Business meal",
    "category": "Training",
    "recipient": "Electric Company",
    "isRecurring": false
  },
  {
    "id": "b0ab0dd4-0d8d-4344-a6ce-db13aa32897a",
    "date": "2024-05-01",
    "amount": 214.88,
    "currency": "ILS",
    "type": "income",
    "createdAt": "2024-05-01T00:00:00Z",
    "updatedAt": "2024-05-01T00:00:00Z",
    "description": "Refund",
    "category": "Salary",
    "recipient": "Landlord",
    "isRecurring": false,
    "isChomesh": true
  },
  {
    "id": "533da32e-1f37-4537-bf5f-746ce90750e3",
    "date": "2024-05-01",
    "amount": 837.76,
    "currency": "ILS",
    "type": "income",
    "createdAt": "2024-05-01T00:00:00Z",
    "updatedAt": "2024-05-01T00:00:00Z",
    "description": "Salary",
    "category": "Freelance",
    "recipient": "Landlord",
    "isRecurring": false,
    "isChomesh": true
  },
  {
    "id": "f81737a3-dbed-496c-96de-afbb2f959d20",
    "date": "2024-05-01",
    "amount": 381.58,
    "currency": "ILS",
    "type": "income",
    "createdAt": "2024-05-01T00:00:00Z",
    "updatedAt": "2024-05-01T00:00:00Z",
    "description": "Freelance work",
    "category": "Refund",
    "recipient": "Landlord",
    "isRecurring": false,
    "isChomesh": true
  },
  {
    "id": "d717dbdb-da1f-482d-92c2-5ed07f56e13a",
    "date": "2024-05-01",
    "amount": 2198.25,
    "currency": "ILS",
    "type": "income",
    "createdAt": "2024-05-01T00:00:00Z",
    "updatedAt": "2024-05-01T00:00:00Z",
    "description": "Freelance work",
    "category": "Salary",
    "recipient": "Yossi Cohen",
    "isRecurring": false,
    "isChomesh": true
  },
  {
    "id": "5cb64dd4-5a68-436b-8690-2ffc461f95a3",
    "date": "2024-05-01",
    "amount": 2427.26,
    "currency": "ILS",
    "type": "recognized-expense",
    "createdAt": "2024-05-01T00:00:00Z",
    "updatedAt": "2024-05-01T00:00:00Z",
    "description": "Software subscription",
    "category": "Business",
    "recipient": "Employer",
    "isRecurring": false
  },
  {
    "id": "c1964d55-e3d0-48a4-8f92-3f457e7de61a",
    "date": "2024-05-01",
    "amount": 451.47,
    "currency": "ILS",
    "type": "income",
    "createdAt": "2024-05-01T00:00:00Z",
    "updatedAt": "2024-05-01T00:00:00Z",
    "description": "Freelance work",
    "category": "Salary",
    "recipient": "Moshe Levi",
    "isRecurring": false,
    "isChomesh": true
  },
  {
    "id": "c0bc8500-e94a-40d1-8fbe-9595f96075a8",
    "date": "2024-05-01",
    "amount": 2276.54,
    "currency": "ILS",
    "type": "expense",
    "createdAt": "2024-05-01T00:00:00Z",
    "updatedAt": "2024-05-01T00:00:00Z",
    "description": "Restaurant",
    "category": "Transportation",
    "recipient": "Supplier",
    "isRecurring": false
  },
  {
    "id": "99a33384-646a-46d4-8e40-8cd879f30340",
    "date": "2024-05-01",
    "amount": 728.37,
    "currency": "ILS",
    "type": "recognized-expense",
    "createdAt": "2024-05-01T00:00:00Z",
    "updatedAt": "2024-05-01T00:00:00Z",
    "description": "Software subscription",
    "category": "Business",
    "recipient": "Partner",
    "isRecurring": false
  },
  {
    "id": "9160ced2-8930-4bba-ac86-3f9f41fbb736",
    "date": "2024-06-01",
    "amount": 2446.43,
    "currency": "ILS",
    "type": "income",
    "createdAt": "2024-06-01T00:00:00Z",
    "updatedAt": "2024-06-01T00:00:00Z",
    "description": "Bonus",
    "category": "Salary",
    "recipient": "Supplier",
    "isRecurring": true,
    "isChomesh": false,
    "recurringDayOfMonth": 23,
    "recurringTotalCount": 12
  },
  {
    "id": "51346cf5-7ca7-4b82-886f-1815812efb26",
    "date": "2024-06-01",
    "amount": 2377.4,
    "currency": "ILS",
    "type": "recognized-expense",
    "createdAt": "2024-06-01T00:00:00Z",
    "updatedAt": "2024-06-01T00:00:00Z",
    "description": "Conference ticket",
    "category": "Business",
    "recipient": "Moshe Levi",
    "isRecurring": false
  },
  {
    "id": "2598b64b-f925-42d2-ac5a-e8df30332623",
    "date": "2024-06-01",
    "amount": 2420.36,
    "currency": "ILS",
    "type": "donation",
    "createdAt": "2024-06-01T00:00:00Z",
    "updatedAt": "2024-06-01T00:00:00Z",
    "description": "Charity for children",
    "category": "Charity",
    "recipient": "Supplier",
    "isRecurring": false
  },
  {
    "id": "4f16c201-c105-4b5c-a38c-06d4d866c082",
    "date": "2024-06-01",
    "amount": 1831.69,
    "currency": "ILS",
    "type": "recognized-expense",
    "createdAt": "2024-06-01T00:00:00Z",
    "updatedAt": "2024-06-01T00:00:00Z",
    "description": "Conference ticket",
    "category": "Tools",
    "recipient": "Moshe Levi",
    "isRecurring": false
  },
  {
    "id": "1200714a-b647-4b79-becd-ba732addb130",
    "date": "2024-06-01",
    "amount": 1717.39,
    "currency": "ILS",
    "type": "expense",
    "createdAt": "2024-06-01T00:00:00Z",
    "updatedAt": "2024-06-01T00:00:00Z",
    "description": "Rent",
    "category": "Living",
    "recipient": "Partner",
    "isRecurring": false
  },
  {
    "id": "1d390cf2-6bd8-4d1c-a278-8ff3a9dcfafd",
    "date": "2024-06-01",
    "amount": 1464.05,
    "currency": "ILS",
    "type": "income",
    "createdAt": "2024-06-01T00:00:00Z",
    "updatedAt": "2024-06-01T00:00:00Z",
    "description": "Salary",
    "category": "Salary",
    "recipient": "Yossi Cohen",
    "isRecurring": false,
    "isChomesh": true
  },
  {
    "id": "0c2b5375-02b4-44cd-908e-8313aa03bdda",
    "date": "2024-06-01",
    "amount": 2372.96,
    "currency": "ILS",
    "type": "expense",
    "createdAt": "2024-06-01T00:00:00Z",
    "updatedAt": "2024-06-01T00:00:00Z",
    "description": "Phone bill",
    "category": "Utilities",
    "recipient": "Landlord",
    "isRecurring": false
  },
  {
    "id": "123ae983-fb7b-4515-844d-d17d2f043746",
    "date": "2024-06-01",
    "amount": 85.14,
    "currency": "ILS",
    "type": "income",
    "createdAt": "2024-06-01T00:00:00Z",
    "updatedAt": "2024-06-01T00:00:00Z",
    "description": "Freelance work",
    "category": "Refund",
    "recipient": "Supplier",
    "isRecurring": false,
    "isChomesh": true
  },
  {
    "id": "083da31a-d9ad-4e4d-bfde-a386a8e688ac",
    "date": "2024-07-01",
    "amount": 589.92,
    "currency": "ILS",
    "type": "donation",
    "createdAt": "2024-07-01T00:00:00Z",
    "updatedAt": "2024-07-01T00:00:00Z",
    "description": "Charity for children",
    "category": "Religious",
    "recipient": "Employer",
    "isRecurring": false
  },
  {
    "id": "349f4f8e-158c-450f-816f-0e3cab7896bd",
    "date": "2024-07-01",
    "amount": 573.53,
    "currency": "ILS",
    "type": "expense",
    "createdAt": "2024-07-01T00:00:00Z",
    "updatedAt": "2024-07-01T00:00:00Z",
    "description": "Restaurant",
    "category": "Transportation",
    "recipient": "Moshe Levi",
    "isRecurring": false
  },
  {
    "id": "1b294e41-ef61-4055-a588-4bf19d4a9f64",
    "date": "2024-07-01",
    "amount": 620.97,
    "currency": "ILS",
    "type": "donation",
    "createdAt": "2024-07-01T00:00:00Z",
    "updatedAt": "2024-07-01T00:00:00Z",
    "description": "Zaka donation",
    "category": "Religious",
    "recipient": "Employer",
    "isRecurring": false
  },
  {
    "id": "8e92372f-66f2-42b8-8298-d5ad1904c07d",
    "date": "2024-07-01",
    "amount": 1320.19,
    "currency": "ILS",
    "type": "expense",
    "createdAt": "2024-07-01T00:00:00Z",
    "updatedAt": "2024-07-01T00:00:00Z",
    "description": "Electricity bill",
    "category": "Living",
    "recipient": "Partner",
    "isRecurring": false
  },
  {
    "id": "9f8c149c-4001-418b-ab9d-26a0f72a02f4",
    "date": "2024-07-01",
    "amount": 2121.44,
    "currency": "ILS",
    "type": "recognized-expense",
    "createdAt": "2024-07-01T00:00:00Z",
    "updatedAt": "2024-07-01T00:00:00Z",
    "description": "Work travel",
    "category": "Training",
    "recipient": "Chabad House",
    "isRecurring": false
  },
  {
    "id": "652090aa-6c13-4f5d-b207-68a7f79f0b24",
    "date": "2024-07-01",
    "amount": 791.42,
    "currency": "ILS",
    "type": "donation",
    "createdAt": "2024-07-01T00:00:00Z",
    "updatedAt": "2024-07-01T00:00:00Z",
    "description": "Yeshiva support",
    "category": "Charity",
    "recipient": "Electric Company",
    "isRecurring": false
  },
  {
    "id": "b0c4a73a-9f16-4233-9ce6-19128286e64a",
    "date": "2024-07-01",
    "amount": 394.42,
    "currency": "ILS",
    "type": "recognized-expense",
    "createdAt": "2024-07-01T00:00:00Z",
    "updatedAt": "2024-07-01T00:00:00Z",
    "description": "Work travel",
    "category": "Business",
    "recipient": "Yossi Cohen",
    "isRecurring": false
  },
  {
    "id": "e2ce9e6f-fa57-4856-a2f9-5860728967eb",
    "date": "2024-07-01",
    "amount": 1474.58,
    "currency": "ILS",
    "type": "recognized-expense",
    "createdAt": "2024-07-01T00:00:00Z",
    "updatedAt": "2024-07-01T00:00:00Z",
    "description": "Business meal",
    "category": "Business",
    "recipient": "Supplier",
    "isRecurring": false
  },
  {
    "id": "95b174de-d9b8-4139-912d-43694e4243a9",
    "date": "2024-08-01",
    "amount": 1365.64,
    "currency": "ILS",
    "type": "donation",
    "createdAt": "2024-08-01T00:00:00Z",
    "updatedAt": "2024-08-01T00:00:00Z",
    "description": "Charity for children",
    "category": "Religious",
    "recipient": "Landlord",
    "isRecurring": true,
    "recurringDayOfMonth": 19,
    "recurringTotalCount": 9
  },
  {
    "id": "69a65822-2d47-4aeb-8f76-36cf1a16408d",
    "date": "2024-08-01",
    "amount": 957.84,
    "currency": "ILS",
    "type": "donation",
    "createdAt": "2024-08-01T00:00:00Z",
    "updatedAt": "2024-08-01T00:00:00Z",
    "description": "Donation to synagogue",
    "category": "Charity",
    "recipient": "Moshe Levi",
    "isRecurring": false
  },
  {
    "id": "134ac445-aba4-49fc-bf0a-64d31b913965",
    "date": "2024-08-01",
    "amount": 1968.24,
    "currency": "ILS",
    "type": "income",
    "createdAt": "2024-08-01T00:00:00Z",
    "updatedAt": "2024-08-01T00:00:00Z",
    "description": "Freelance work",
    "category": "Refund",
    "recipient": "Moshe Levi",
    "isRecurring": false,
    "isChomesh": false
  },
  {
    "id": "ec4667e1-01da-485b-820e-bb8ad12c0770",
    "date": "2024-08-01",
    "amount": 1048.22,
    "currency": "ILS",
    "type": "donation",
    "createdAt": "2024-08-01T00:00:00Z",
    "updatedAt": "2024-08-01T00:00:00Z",
    "description": "Donation to synagogue",
    "category": "Education",
    "recipient": "Supplier",
    "isRecurring": false
  },
  {
    "id": "e07419d8-30ea-4f7f-808e-43a5edec5816",
    "date": "2024-08-01",
    "amount": 54.88,
    "currency": "ILS",
    "type": "recognized-expense",
    "createdAt": "2024-08-01T00:00:00Z",
    "updatedAt": "2024-08-01T00:00:00Z",
    "description": "Software subscription",
    "category": "Training",
    "recipient": "Landlord",
    "isRecurring": false
  },
  {
    "id": "3d77dfd8-92ad-469f-81e6-bb6891b51fb2",
    "date": "2024-08-01",
    "amount": 1114.46,
    "currency": "ILS",
    "type": "recognized-expense",
    "createdAt": "2024-08-01T00:00:00Z",
    "updatedAt": "2024-08-01T00:00:00Z",
    "description": "Software subscription",
    "category": "Tools",
    "recipient": "Supplier",
    "isRecurring": false
  },
  {
    "id": "420efb55-a57d-4ac1-b4a1-dab15e37f5df",
    "date": "2024-08-01",
    "amount": 899.5,
    "currency": "ILS",
    "type": "recognized-expense",
    "createdAt": "2024-08-01T00:00:00Z",
    "updatedAt": "2024-08-01T00:00:00Z",
    "description": "Software subscription",
    "category": "Business",
    "recipient": "Yossi Cohen",
    "isRecurring": false
  },
  {
    "id": "6784f781-4aa6-4d24-aa1a-2af226e5a7b9",
    "date": "2024-08-01",
    "amount": 839.69,
    "currency": "ILS",
    "type": "expense",
    "createdAt": "2024-08-01T00:00:00Z",
    "updatedAt": "2024-08-01T00:00:00Z",
    "description": "Restaurant",
    "category": "Entertainment",
    "recipient": "Employer",
    "isRecurring": false
  },
  {
    "id": "469537dc-d882-43b6-b631-5c169383e0d6",
    "date": "2024-09-01",
    "amount": 1556.02,
    "currency": "ILS",
    "type": "donation",
    "createdAt": "2024-09-01T00:00:00Z",
    "updatedAt": "2024-09-01T00:00:00Z",
    "description": "Yeshiva support",
    "category": "Charity",
    "recipient": "Supplier",
    "isRecurring": false
  },
  {
    "id": "bdb33ffc-6c79-429a-a219-0e2d9fe7b122",
    "date": "2024-09-01",
    "amount": 1216.62,
    "currency": "ILS",
    "type": "donation",
    "createdAt": "2024-09-01T00:00:00Z",
    "updatedAt": "2024-09-01T00:00:00Z",
    "description": "Donation to synagogue",
    "category": "Charity",
    "recipient": "Electric Company",
    "isRecurring": false
  },
  {
    "id": "104b9563-b186-488c-ac24-0b76293db932",
    "date": "2024-09-01",
    "amount": 2446.07,
    "currency": "ILS",
    "type": "income",
    "createdAt": "2024-09-01T00:00:00Z",
    "updatedAt": "2024-09-01T00:00:00Z",
    "description": "Freelance work",
    "category": "Salary",
    "recipient": "Chabad House",
    "isRecurring": false,
    "isChomesh": true
  },
  {
    "id": "6bf6304d-abca-4c72-b736-233c8a71752b",
    "date": "2024-09-01",
    "amount": 1059.21,
    "currency": "ILS",
    "type": "donation",
    "createdAt": "2024-09-01T00:00:00Z",
    "updatedAt": "2024-09-01T00:00:00Z",
    "description": "Zaka donation",
    "category": "Charity",
    "recipient": "Partner",
    "isRecurring": true,
    "recurringDayOfMonth": 20,
    "recurringTotalCount": 5
  },
  {
    "id": "82d107b7-137c-4134-9bec-54ae6c115261",
    "date": "2024-09-01",
    "amount": 1829.9,
    "currency": "ILS",
    "type": "donation",
    "createdAt": "2024-09-01T00:00:00Z",
    "updatedAt": "2024-09-01T00:00:00Z",
    "description": "Donation to synagogue",
    "category": "Education",
    "recipient": "Supplier",
    "isRecurring": true,
    "recurringDayOfMonth": 4,
    "recurringTotalCount": 2
  },
  {
    "id": "11ea6ea7-5401-47a9-8f40-8410bfb0cfb9",
    "date": "2024-09-01",
    "amount": 1345.82,
    "currency": "ILS",
    "type": "recognized-expense",
    "createdAt": "2024-09-01T00:00:00Z",
    "updatedAt": "2024-09-01T00:00:00Z",
    "description": "Conference ticket",
    "category": "Training",
    "recipient": "Supplier",
    "isRecurring": false
  },
  {
    "id": "2a452d06-42f0-44cf-b17f-edb66624deb9",
    "date": "2024-09-01",
    "amount": 1867.48,
    "currency": "ILS",
    "type": "recognized-expense",
    "createdAt": "2024-09-01T00:00:00Z",
    "updatedAt": "2024-09-01T00:00:00Z",
    "description": "Conference ticket",
    "category": "Business",
    "recipient": "Electric Company",
    "isRecurring": true,
    "recurringDayOfMonth": 24,
    "recurringTotalCount": 6
  },
  {
    "id": "f5aa6e4c-c797-4093-b117-52054c27c881",
    "date": "2024-09-01",
    "amount": 1479.62,
    "currency": "ILS",
    "type": "donation",
    "createdAt": "2024-09-01T00:00:00Z",
    "updatedAt": "2024-09-01T00:00:00Z",
    "description": "Charity for children",
    "category": "Religious",
    "recipient": "Electric Company",
    "isRecurring": false
  },
  {
    "id": "994b969f-de5f-4ba5-83f4-00129b711aab",
    "date": "2024-10-01",
    "amount": 2468.01,
    "currency": "ILS",
    "type": "expense",
    "createdAt": "2024-10-01T00:00:00Z",
    "updatedAt": "2024-10-01T00:00:00Z",
    "description": "Fuel",
    "category": "Transportation",
    "recipient": "Employer",
    "isRecurring": true,
    "recurringDayOfMonth": 5,
    "recurringTotalCount": 6
  },
  {
    "id": "fb1c5314-f633-4e8f-a719-929d0b2d607a",
    "date": "2024-10-01",
    "amount": 184.09,
    "currency": "ILS",
    "type": "expense",
    "createdAt": "2024-10-01T00:00:00Z",
    "updatedAt": "2024-10-01T00:00:00Z",
    "description": "Clothing",
    "category": "Living",
    "recipient": "Partner",
    "isRecurring": false
  },
  {
    "id": "2644209a-acd2-47c2-884e-0c432989d375",
    "date": "2024-10-01",
    "amount": 147.93,
    "currency": "ILS",
    "type": "recognized-expense",
    "createdAt": "2024-10-01T00:00:00Z",
    "updatedAt": "2024-10-01T00:00:00Z",
    "description": "Business meal",
    "category": "Training",
    "recipient": "Electric Company",
    "isRecurring": true,
    "recurringDayOfMonth": 15,
    "recurringTotalCount": 6
  },
  {
    "id": "529ae680-aebd-439d-96bb-811f59d0b29b",
    "date": "2024-10-01",
    "amount": 1254.55,
    "currency": "ILS",
    "type": "donation",
    "createdAt": "2024-10-01T00:00:00Z",
    "updatedAt": "2024-10-01T00:00:00Z",
    "description": "Zaka donation",
    "category": "Religious",
    "recipient": "Yossi Cohen",
    "isRecurring": false
  },
  {
    "id": "09bfe7e6-239e-4da5-9c26-9705259b7282",
    "date": "2024-10-01",
    "amount": 1021.24,
    "currency": "ILS",
    "type": "expense",
    "createdAt": "2024-10-01T00:00:00Z",
    "updatedAt": "2024-10-01T00:00:00Z",
    "description": "Electricity bill",
    "category": "Entertainment",
    "recipient": "Electric Company",
    "isRecurring": false
  },
  {
    "id": "c640b76f-ae85-4893-9532-d32eb22ab656",
    "date": "2024-10-01",
    "amount": 559.35,
    "currency": "ILS",
    "type": "recognized-expense",
    "createdAt": "2024-10-01T00:00:00Z",
    "updatedAt": "2024-10-01T00:00:00Z",
    "description": "Work travel",
    "category": "Tools",
    "recipient": "Partner",
    "isRecurring": false
  },
  {
    "id": "0f8885f4-c5b2-40c0-85e3-873705a3f2f4",
    "date": "2024-10-01",
    "amount": 1131.92,
    "currency": "ILS",
    "type": "expense",
    "createdAt": "2024-10-01T00:00:00Z",
    "updatedAt": "2024-10-01T00:00:00Z",
    "description": "Fuel",
    "category": "Transportation",
    "recipient": "Yossi Cohen",
    "isRecurring": false
  },
  {
    "id": "07907148-67a3-4870-834a-f7b26e13f3fd",
    "date": "2024-10-01",
    "amount": 660.71,
    "currency": "ILS",
    "type": "recognized-expense",
    "createdAt": "2024-10-01T00:00:00Z",
    "updatedAt": "2024-10-01T00:00:00Z",
    "description": "Conference ticket",
    "category": "Business",
    "recipient": "Yossi Cohen",
    "isRecurring": false
  },
  {
    "id": "90a2e742-11fc-417a-95c1-f43a601c61e5",
    "date": "2024-11-01",
    "amount": 2300.63,
    "currency": "ILS",
    "type": "expense",
    "createdAt": "2024-11-01T00:00:00Z",
    "updatedAt": "2024-11-01T00:00:00Z",
    "description": "Electricity bill",
    "category": "Utilities",
    "recipient": "Moshe Levi",
    "isRecurring": false
  },
  {
    "id": "5e4f24d3-6830-405a-8bc7-48e7f769b279",
    "date": "2024-11-01",
    "amount": 2027.08,
    "currency": "ILS",
    "type": "income",
    "createdAt": "2024-11-01T00:00:00Z",
    "updatedAt": "2024-11-01T00:00:00Z",
    "description": "Refund",
    "category": "Freelance",
    "recipient": "Landlord",
    "isRecurring": false,
    "isChomesh": true
  },
  {
    "id": "386db6ad-ada5-42aa-9f0b-7f24b851f43f",
    "date": "2024-11-01",
    "amount": 1041.02,
    "currency": "ILS",
    "type": "recognized-expense",
    "createdAt": "2024-11-01T00:00:00Z",
    "updatedAt": "2024-11-01T00:00:00Z",
    "description": "Conference ticket",
    "category": "Tools",
    "recipient": "Chabad House",
    "isRecurring": true,
    "recurringDayOfMonth": 18,
    "recurringTotalCount": 8
  },
  {
    "id": "c0d138f0-73cc-406d-add0-0e8cccba6d57",
    "date": "2024-11-01",
    "amount": 936.67,
    "currency": "ILS",
    "type": "expense",
    "createdAt": "2024-11-01T00:00:00Z",
    "updatedAt": "2024-11-01T00:00:00Z",
    "description": "Internet",
    "category": "Food",
    "recipient": "Employer",
    "isRecurring": false
  },
  {
    "id": "7f029058-3632-4565-9fb1-628dc59f8c76",
    "date": "2024-11-01",
    "amount": 2320.61,
    "currency": "ILS",
    "type": "recognized-expense",
    "createdAt": "2024-11-01T00:00:00Z",
    "updatedAt": "2024-11-01T00:00:00Z",
    "description": "Conference ticket",
    "category": "Business",
    "recipient": "Moshe Levi",
    "isRecurring": false
  },
  {
    "id": "ef829f07-c6b5-4337-8072-145e91f75af6",
    "date": "2024-11-01",
    "amount": 938.48,
    "currency": "ILS",
    "type": "recognized-expense",
    "createdAt": "2024-11-01T00:00:00Z",
    "updatedAt": "2024-11-01T00:00:00Z",
    "description": "Conference ticket",
    "category": "Tools",
    "recipient": "Moshe Levi",
    "isRecurring": false
  },
  {
    "id": "f797c9f1-ebee-43ab-a97a-274d70af47aa",
    "date": "2024-11-01",
    "amount": 2322.08,
    "currency": "ILS",
    "type": "donation",
    "createdAt": "2024-11-01T00:00:00Z",
    "updatedAt": "2024-11-01T00:00:00Z",
    "description": "Charity for children",
    "category": "Religious",
    "recipient": "Supplier",
    "isRecurring": true,
    "recurringDayOfMonth": 14,
    "recurringTotalCount": 6
  },
  {
    "id": "2010ef9a-bad1-4031-aed0-dea1dbb019ec",
    "date": "2024-11-01",
    "amount": 1280.38,
    "currency": "ILS",
    "type": "expense",
    "createdAt": "2024-11-01T00:00:00Z",
    "updatedAt": "2024-11-01T00:00:00Z",
    "description": "Internet",
    "category": "Food",
    "recipient": "Landlord",
    "isRecurring": true,
    "recurringDayOfMonth": 20,
    "recurringTotalCount": 12
  },
  {
    "id": "b1ee502a-48a4-4061-b959-97ed8c31d259",
    "date": "2024-12-01",
    "amount": 2427.82,
    "currency": "ILS",
    "type": "donation",
    "createdAt": "2024-12-01T00:00:00Z",
    "updatedAt": "2024-12-01T00:00:00Z",
    "description": "Yeshiva support",
    "category": "Education",
    "recipient": "Chabad House",
    "isRecurring": false
  },
  {
    "id": "8dcea603-5993-487b-bae5-43bd25ae75f1",
    "date": "2024-12-01",
    "amount": 477.8,
    "currency": "ILS",
    "type": "donation",
    "createdAt": "2024-12-01T00:00:00Z",
    "updatedAt": "2024-12-01T00:00:00Z",
    "description": "Zaka donation",
    "category": "Education",
    "recipient": "Supplier",
    "isRecurring": false
  },
  {
    "id": "dc888c50-bfbf-48d4-8aa0-82b72e94540d",
    "date": "2024-12-01",
    "amount": 980.73,
    "currency": "ILS",
    "type": "donation",
    "createdAt": "2024-12-01T00:00:00Z",
    "updatedAt": "2024-12-01T00:00:00Z",
    "description": "Zaka donation",
    "category": "Education",
    "recipient": "Moshe Levi",
    "isRecurring": false
  },
  {
    "id": "1e8f7d4d-d656-4ed0-b362-87148007579d",
    "date": "2024-12-01",
    "amount": 2445.22,
    "currency": "ILS",
    "type": "expense",
    "createdAt": "2024-12-01T00:00:00Z",
    "updatedAt": "2024-12-01T00:00:00Z",
    "description": "Electricity bill",
    "category": "Living",
    "recipient": "Yossi Cohen",
    "isRecurring": false
  },
  {
    "id": "7e8f8f4c-3e0a-4adf-82b0-656c3c55638b",
    "date": "2024-12-01",
    "amount": 2476.65,
    "currency": "ILS",
    "type": "recognized-expense",
    "createdAt": "2024-12-01T00:00:00Z",
    "updatedAt": "2024-12-01T00:00:00Z",
    "description": "Work travel",
    "category": "Training",
    "recipient": "Yossi Cohen",
    "isRecurring": false
  },
  {
    "id": "724184ba-48db-4d2c-8532-eb276d82f914",
    "date": "2024-12-01",
    "amount": 2356.88,
    "currency": "ILS",
    "type": "expense",
    "createdAt": "2024-12-01T00:00:00Z",
    "updatedAt": "2024-12-01T00:00:00Z",
    "description": "Fuel",
    "category": "Food",
    "recipient": "Chabad House",
    "isRecurring": false
  },
  {
    "id": "55599b07-c113-453d-a329-6fdaa6c4f4ca",
    "date": "2024-12-01",
    "amount": 1184.83,
    "currency": "ILS",
    "type": "income",
    "createdAt": "2024-12-01T00:00:00Z",
    "updatedAt": "2024-12-01T00:00:00Z",
    "description": "Bonus",
    "category": "Salary",
    "recipient": "Yossi Cohen",
    "isRecurring": false,
    "isChomesh": false
  },
  {
    "id": "308575b2-308a-4c5c-896b-d9f7f1b795af",
    "date": "2024-12-01",
    "amount": 837.97,
    "currency": "ILS",
    "type": "expense",
    "createdAt": "2024-12-01T00:00:00Z",
    "updatedAt": "2024-12-01T00:00:00Z",
    "description": "Clothing",
    "category": "Entertainment",
    "recipient": "Chabad House",
    "isRecurring": true,
    "recurringDayOfMonth": 4,
    "recurringTotalCount": 12
  },
  {
    "id": "dddc4c41-3d20-4f31-bcfa-9fea419a4ac7",
    "date": "2025-01-01",
    "amount": 2470.98,
    "currency": "ILS",
    "type": "income",
    "createdAt": "2025-01-01T00:00:00Z",
    "updatedAt": "2025-01-01T00:00:00Z",
    "description": "Bonus",
    "category": "Refund",
    "recipient": "Landlord",
    "isRecurring": true,
    "isChomesh": true,
    "recurringDayOfMonth": 4,
    "recurringTotalCount": 3
  },
  {
    "id": "22466925-4455-4000-aea3-b7fe0fa7d96f",
    "date": "2025-01-01",
    "amount": 692.14,
    "currency": "ILS",
    "type": "income",
    "createdAt": "2025-01-01T00:00:00Z",
    "updatedAt": "2025-01-01T00:00:00Z",
    "description": "Freelance work",
    "category": "Freelance",
    "recipient": "Supplier",
    "isRecurring": false,
    "isChomesh": true
  },
  {
    "id": "354e3faf-41d0-44b3-903f-04534681d9f7",
    "date": "2025-01-01",
    "amount": 1166.21,
    "currency": "ILS",
    "type": "income",
    "createdAt": "2025-01-01T00:00:00Z",
    "updatedAt": "2025-01-01T00:00:00Z",
    "description": "Salary",
    "category": "Refund",
    "recipient": "Electric Company",
    "isRecurring": false,
    "isChomesh": true
  },
  {
    "id": "f7f73532-1b3d-4397-ad6d-bee3a40cb98e",
    "date": "2025-01-01",
    "amount": 2492.89,
    "currency": "ILS",
    "type": "recognized-expense",
    "createdAt": "2025-01-01T00:00:00Z",
    "updatedAt": "2025-01-01T00:00:00Z",
    "description": "Work travel",
    "category": "Training",
    "recipient": "Moshe Levi",
    "isRecurring": true,
    "recurringDayOfMonth": 18,
    "recurringTotalCount": 8
  },
  {
    "id": "70687ec8-6652-4f87-aa5b-a790353ef9be",
    "date": "2025-01-01",
    "amount": 759.04,
    "currency": "ILS",
    "type": "donation",
    "createdAt": "2025-01-01T00:00:00Z",
    "updatedAt": "2025-01-01T00:00:00Z",
    "description": "Donation to synagogue",
    "category": "Charity",
    "recipient": "Moshe Levi",
    "isRecurring": false
  },
  {
    "id": "57fc86f1-d58f-4298-ba67-d3fd63429731",
    "date": "2025-01-01",
    "amount": 630.61,
    "currency": "ILS",
    "type": "expense",
    "createdAt": "2025-01-01T00:00:00Z",
    "updatedAt": "2025-01-01T00:00:00Z",
    "description": "Phone bill",
    "category": "Living",
    "recipient": "Supplier",
    "isRecurring": true,
    "recurringDayOfMonth": 13,
    "recurringTotalCount": 9
  },
  {
    "id": "f89495a5-de7f-4214-8336-bc56a96a3ab8",
    "date": "2025-01-01",
    "amount": 1139.02,
    "currency": "ILS",
    "type": "recognized-expense",
    "createdAt": "2025-01-01T00:00:00Z",
    "updatedAt": "2025-01-01T00:00:00Z",
    "description": "Work travel",
    "category": "Tools",
    "recipient": "Yossi Cohen",
    "isRecurring": false
  },
  {
    "id": "9c66e67b-965c-4917-9891-bdbe94c2fbe4",
    "date": "2025-01-01",
    "amount": 210.98,
    "currency": "ILS",
    "type": "income",
    "createdAt": "2025-01-01T00:00:00Z",
    "updatedAt": "2025-01-01T00:00:00Z",
    "description": "Refund",
    "category": "Freelance",
    "recipient": "Yossi Cohen",
    "isRecurring": false,
    "isChomesh": true
  },
  {
    "id": "ca2b465d-88b2-42d3-921c-8735d1f1e7ec",
    "date": "2025-02-01",
    "amount": 863.73,
    "currency": "ILS",
    "type": "donation",
    "createdAt": "2025-02-01T00:00:00Z",
    "updatedAt": "2025-02-01T00:00:00Z",
    "description": "Zaka donation",
    "category": "Education",
    "recipient": "Chabad House",
    "isRecurring": true,
    "recurringDayOfMonth": 10,
    "recurringTotalCount": 8
  },
  {
    "id": "41ea3b88-f91b-4ef7-80c2-173952bca017",
    "date": "2025-02-01",
    "amount": 1836.36,
    "currency": "ILS",
    "type": "donation",
    "createdAt": "2025-02-01T00:00:00Z",
    "updatedAt": "2025-02-01T00:00:00Z",
    "description": "Charity for children",
    "category": "Charity",
    "recipient": "Landlord",
    "isRecurring": false
  },
  {
    "id": "ff4cf3a4-1881-4225-ae46-2c7f6fea9bc4",
    "date": "2025-02-01",
    "amount": 1459.42,
    "currency": "ILS",
    "type": "income",
    "createdAt": "2025-02-01T00:00:00Z",
    "updatedAt": "2025-02-01T00:00:00Z",
    "description": "Bonus",
    "category": "Freelance",
    "recipient": "Moshe Levi",
    "isRecurring": false,
    "isChomesh": true
  },
  {
    "id": "3a7eb9bf-b5f2-46ce-b7fb-9c2970610566",
    "date": "2025-02-01",
    "amount": 1483.42,
    "currency": "ILS",
    "type": "donation",
    "createdAt": "2025-02-01T00:00:00Z",
    "updatedAt": "2025-02-01T00:00:00Z",
    "description": "Donation to synagogue",
    "category": "Charity",
    "recipient": "Landlord",
    "isRecurring": false
  },
  {
    "id": "c23e2c62-ffd0-49e9-85fa-5fad50935236",
    "date": "2025-02-01",
    "amount": 2210.64,
    "currency": "ILS",
    "type": "recognized-expense",
    "createdAt": "2025-02-01T00:00:00Z",
    "updatedAt": "2025-02-01T00:00:00Z",
    "description": "Work travel",
    "category": "Business",
    "recipient": "Landlord",
    "isRecurring": true,
    "recurringDayOfMonth": 14,
    "recurringTotalCount": 8
  },
  {
    "id": "cacd80e1-229a-4199-af34-23215a2bf1e9",
    "date": "2025-02-01",
    "amount": 379.98,
    "currency": "ILS",
    "type": "recognized-expense",
    "createdAt": "2025-02-01T00:00:00Z",
    "updatedAt": "2025-02-01T00:00:00Z",
    "description": "Work travel",
    "category": "Training",
    "recipient": "Partner",
    "isRecurring": false
  },
  {
    "id": "253f147f-0446-4261-84f6-2f82355c42bb",
    "date": "2025-02-01",
    "amount": 2345.99,
    "currency": "ILS",
    "type": "expense",
    "createdAt": "2025-02-01T00:00:00Z",
    "updatedAt": "2025-02-01T00:00:00Z",
    "description": "Fuel",
    "category": "Food",
    "recipient": "Chabad House",
    "isRecurring": false
  },
  {
    "id": "f3eb2037-1f5b-4072-ba16-05bc9bad00e1",
    "date": "2025-02-01",
    "amount": 1660.46,
    "currency": "ILS",
    "type": "recognized-expense",
    "createdAt": "2025-02-01T00:00:00Z",
    "updatedAt": "2025-02-01T00:00:00Z",
    "description": "Software subscription",
    "category": "Training",
    "recipient": "Electric Company",
    "isRecurring": false
  },
  {
    "id": "9fd0c6ed-dc36-4626-8a8e-72da2530ce94",
    "date": "2025-03-01",
    "amount": 280.95,
    "currency": "ILS",
    "type": "expense",
    "createdAt": "2025-03-01T00:00:00Z",
    "updatedAt": "2025-03-01T00:00:00Z",
    "description": "Fuel",
    "category": "Food",
    "recipient": "Supplier",
    "isRecurring": false
  },
  {
    "id": "fadddc03-b383-4bd6-aea0-58e4314d562f",
    "date": "2025-03-01",
    "amount": 1229.31,
    "currency": "ILS",
    "type": "donation",
    "createdAt": "2025-03-01T00:00:00Z",
    "updatedAt": "2025-03-01T00:00:00Z",
    "description": "Zaka donation",
    "category": "Religious",
    "recipient": "Employer",
    "isRecurring": false
  },
  {
    "id": "e45e0f20-a884-4509-b81f-0a89ebd8a8e6",
    "date": "2025-03-01",
    "amount": 784.79,
    "currency": "ILS",
    "type": "recognized-expense",
    "createdAt": "2025-03-01T00:00:00Z",
    "updatedAt": "2025-03-01T00:00:00Z",
    "description": "Software subscription",
    "category": "Training",
    "recipient": "Moshe Levi",
    "isRecurring": false
  },
  {
    "id": "b8d7d420-0da1-49e0-94ca-712b4916ebab",
    "date": "2025-03-01",
    "amount": 227.08,
    "currency": "ILS",
    "type": "donation",
    "createdAt": "2025-03-01T00:00:00Z",
    "updatedAt": "2025-03-01T00:00:00Z",
    "description": "Yeshiva support",
    "category": "Religious",
    "recipient": "Electric Company",
    "isRecurring": true,
    "recurringDayOfMonth": 12,
    "recurringTotalCount": 3
  },
  {
    "id": "77969e65-3053-4a99-93c9-1ade0f3ba65b",
    "date": "2025-03-01",
    "amount": 971.18,
    "currency": "ILS",
    "type": "income",
    "createdAt": "2025-03-01T00:00:00Z",
    "updatedAt": "2025-03-01T00:00:00Z",
    "description": "Refund",
    "category": "Salary",
    "recipient": "Employer",
    "isRecurring": true,
    "isChomesh": true,
    "recurringDayOfMonth": 4,
    "recurringTotalCount": 8
  },
  {
    "id": "b68c3548-a0bc-4394-89ed-10b4aa12893e",
    "date": "2025-03-01",
    "amount": 192.32,
    "currency": "ILS",
    "type": "income",
    "createdAt": "2025-03-01T00:00:00Z",
    "updatedAt": "2025-03-01T00:00:00Z",
    "description": "Bonus",
    "category": "Freelance",
    "recipient": "Landlord",
    "isRecurring": true,
    "isChomesh": true,
    "recurringDayOfMonth": 14,
    "recurringTotalCount": 4
  },
  {
    "id": "f521642e-1d75-4cc1-a7f1-5ce82299e3de",
    "date": "2025-03-01",
    "amount": 1067.65,
    "currency": "ILS",
    "type": "expense",
    "createdAt": "2025-03-01T00:00:00Z",
    "updatedAt": "2025-03-01T00:00:00Z",
    "description": "Phone bill",
    "category": "Transportation",
    "recipient": "Employer",
    "isRecurring": false
  },
  {
    "id": "ce2c8edf-f31d-4a40-9710-f50504640668",
    "date": "2025-03-01",
    "amount": 1700.72,
    "currency": "ILS",
    "type": "expense",
    "createdAt": "2025-03-01T00:00:00Z",
    "updatedAt": "2025-03-01T00:00:00Z",
    "description": "Groceries",
    "category": "Food",
    "recipient": "Moshe Levi",
    "isRecurring": true,
    "recurringDayOfMonth": 9,
    "recurringTotalCount": 10
  },
  {
    "id": "29a8d52d-2dd6-4dd0-8c47-77c81b03795b",
    "date": "2025-04-01",
    "amount": 268.26,
    "currency": "ILS",
    "type": "donation",
    "createdAt": "2025-04-01T00:00:00Z",
    "updatedAt": "2025-04-01T00:00:00Z",
    "description": "Charity for children",
    "category": "Education",
    "recipient": "Electric Company",
    "isRecurring": true,
    "recurringDayOfMonth": 1,
    "recurringTotalCount": 5
  },
  {
    "id": "e6855d10-15fc-4199-af8b-38ce4f918df1",
    "date": "2025-04-01",
    "amount": 853.81,
    "currency": "ILS",
    "type": "expense",
    "createdAt": "2025-04-01T00:00:00Z",
    "updatedAt": "2025-04-01T00:00:00Z",
    "description": "Restaurant",
    "category": "Living",
    "recipient": "Yossi Cohen",
    "isRecurring": false
  },
  {
    "id": "28119966-f815-4d62-a097-7e22be54b38b",
    "date": "2025-04-01",
    "amount": 563.44,
    "currency": "ILS",
    "type": "expense",
    "createdAt": "2025-04-01T00:00:00Z",
    "updatedAt": "2025-04-01T00:00:00Z",
    "description": "Groceries",
    "category": "Food",
    "recipient": "Moshe Levi",
    "isRecurring": false
  },
  {
    "id": "0e17ecb9-ff61-411d-a04c-9b873ba90326",
    "date": "2025-04-01",
    "amount": 1134.09,
    "currency": "ILS",
    "type": "donation",
    "createdAt": "2025-04-01T00:00:00Z",
    "updatedAt": "2025-04-01T00:00:00Z",
    "description": "Charity for children",
    "category": "Charity",
    "recipient": "Partner",
    "isRecurring": true,
    "recurringDayOfMonth": 27,
    "recurringTotalCount": 8
  },
  {
    "id": "78162f5a-a98f-4be7-a6d7-9ef26f7ed828",
    "date": "2025-04-01",
    "amount": 2346.2,
    "currency": "ILS",
    "type": "donation",
    "createdAt": "2025-04-01T00:00:00Z",
    "updatedAt": "2025-04-01T00:00:00Z",
    "description": "Zaka donation",
    "category": "Education",
    "recipient": "Yossi Cohen",
    "isRecurring": false
  },
  {
    "id": "9de91758-73fd-44fe-814c-e0711baa4f3b",
    "date": "2025-04-01",
    "amount": 1430.35,
    "currency": "ILS",
    "type": "income",
    "createdAt": "2025-04-01T00:00:00Z",
    "updatedAt": "2025-04-01T00:00:00Z",
    "description": "Salary",
    "category": "Refund",
    "recipient": "Electric Company",
    "isRecurring": false,
    "isChomesh": true
  },
  {
    "id": "21cb0e85-e7f8-4b93-8aa9-45018e4ea441",
    "date": "2025-04-01",
    "amount": 625.79,
    "currency": "ILS",
    "type": "income",
    "createdAt": "2025-04-01T00:00:00Z",
    "updatedAt": "2025-04-01T00:00:00Z",
    "description": "Bonus",
    "category": "Refund",
    "recipient": "Moshe Levi",
    "isRecurring": true,
    "isChomesh": true,
    "recurringDayOfMonth": 28,
    "recurringTotalCount": 9
  },
  {
    "id": "0881c0f6-6718-4e68-89ad-f60e06cd7a12",
    "date": "2025-04-01",
    "amount": 845.45,
    "currency": "ILS",
    "type": "income",
    "createdAt": "2025-04-01T00:00:00Z",
    "updatedAt": "2025-04-01T00:00:00Z",
    "description": "Freelance work",
    "category": "Salary",
    "recipient": "Chabad House",
    "isRecurring": true,
    "isChomesh": false,
    "recurringDayOfMonth": 21,
    "recurringTotalCount": 3
  },
  {
    "id": "424a489b-8df4-4ff3-ad2b-313404ab6c1c",
    "date": "2025-05-01",
    "amount": 1212.67,
    "currency": "ILS",
    "type": "recognized-expense",
    "createdAt": "2025-05-01T00:00:00Z",
    "updatedAt": "2025-05-01T00:00:00Z",
    "description": "Software subscription",
    "category": "Tools",
    "recipient": "Landlord",
    "isRecurring": true,
    "recurringDayOfMonth": 25,
    "recurringTotalCount": 9
  },
  {
    "id": "a448ec4a-d493-4958-a266-bc48bc28c74a",
    "date": "2025-05-01",
    "amount": 1143.23,
    "currency": "ILS",
    "type": "income",
    "createdAt": "2025-05-01T00:00:00Z",
    "updatedAt": "2025-05-01T00:00:00Z",
    "description": "Freelance work",
    "category": "Refund",
    "recipient": "Landlord",
    "isRecurring": true,
    "isChomesh": true,
    "recurringDayOfMonth": 11,
    "recurringTotalCount": 9
  },
  {
    "id": "64b66e6c-dd99-4758-bfc1-f183f3d66795",
    "date": "2025-05-01",
    "amount": 1652.01,
    "currency": "ILS",
    "type": "recognized-expense",
    "createdAt": "2025-05-01T00:00:00Z",
    "updatedAt": "2025-05-01T00:00:00Z",
    "description": "Work travel",
    "category": "Training",
    "recipient": "Moshe Levi",
    "isRecurring": false
  },
  {
    "id": "b29ff04d-663d-4543-ac31-4ebbab7dfac2",
    "date": "2025-05-01",
    "amount": 1216.27,
    "currency": "ILS",
    "type": "expense",
    "createdAt": "2025-05-01T00:00:00Z",
    "updatedAt": "2025-05-01T00:00:00Z",
    "description": "Restaurant",
    "category": "Transportation",
    "recipient": "Employer",
    "isRecurring": true,
    "recurringDayOfMonth": 10,
    "recurringTotalCount": 10
  },
  {
    "id": "c1ff3197-0833-453a-839f-2957bb29258a",
    "date": "2025-05-01",
    "amount": 1547.33,
    "currency": "ILS",
    "type": "expense",
    "createdAt": "2025-05-01T00:00:00Z",
    "updatedAt": "2025-05-01T00:00:00Z",
    "description": "Restaurant",
    "category": "Entertainment",
    "recipient": "Partner",
    "isRecurring": false
  },
  {
    "id": "2e8e1c53-dc10-427e-9863-ae34c44031d9",
    "date": "2025-05-01",
    "amount": 200.21,
    "currency": "ILS",
    "type": "expense",
    "createdAt": "2025-05-01T00:00:00Z",
    "updatedAt": "2025-05-01T00:00:00Z",
    "description": "Internet",
    "category": "Living",
    "recipient": "Moshe Levi",
    "isRecurring": false
  },
  {
    "id": "6b7baaf6-a001-4679-9dee-75659b897bc9",
    "date": "2025-05-01",
    "amount": 1039.94,
    "currency": "ILS",
    "type": "recognized-expense",
    "createdAt": "2025-05-01T00:00:00Z",
    "updatedAt": "2025-05-01T00:00:00Z",
    "description": "Conference ticket",
    "category": "Business",
    "recipient": "Yossi Cohen",
    "isRecurring": true,
    "recurringDayOfMonth": 23,
    "recurringTotalCount": 5
  },
  {
    "id": "8e714440-e618-4be2-b758-81df80eefd82",
    "date": "2025-05-01",
    "amount": 175.3,
    "currency": "ILS",
    "type": "expense",
    "createdAt": "2025-05-01T00:00:00Z",
    "updatedAt": "2025-05-01T00:00:00Z",
    "description": "Electricity bill",
    "category": "Food",
    "recipient": "Chabad House",
    "isRecurring": false
  }
]